{
    "vehicle_cost_per_km": [
        5, 
        5, 
        5, 
        5, 
        5
    ], 
    "runs": [
        {
            "avg_task_cost_vs_number_of_task": [
                1038, 
                1146.75, 
                864.1666666666666, 
                654.875, 
                569.2, 
                492.5, 
                518.2857142857143, 
                464.31250000000006, 
                410.1111111111111, 
                468.35, 
                379.09090909090907, 
                360.1666666666667, 
                345.57692307692315, 
                310.2142857142857, 
                352.23333333333335, 
                277.90625, 
                285, 
                263.80555555555554, 
                258.3157894736842, 
                252.875, 
                257.54761904761904, 
                268.54545454545456, 
                208.17391304347825, 
                243.58333333333334, 
                250.08, 
                195.98076923076923, 
                198.59259259259255, 
                202.2678571428571, 
                206.89655172413794, 
                166.66666666666666
            ], 
            "number_of_vehicles": 5
        }
    ], 
    "vehicle_starting_positions": [
        "Amsterdam", 
        "Rotterdam", 
        "Den Haag", 
        "Utrecht", 
        "Eindhoven", 
        "Almere", 
        "Groningen", 
        "Nijmegen", 
        "Breda", 
        "Apeldoorn"
    ], 
    "task_distribution": {
        "distance_matrix": [
            [
                0, 
                90.6, 
                65.2, 
                45.6, 
                137.5, 
                31.9, 
                185.9, 
                132, 
                119.1, 
                90.2
            ], 
            [
                90.6, 
                0, 
                25.4, 
                62.3, 
                110.8, 
                105.6, 
                259.6, 
                112, 
                48.6, 
                129.3
            ], 
            [
                65.2, 
                25.4, 
                0, 
                87.7, 
                136.2, 
                97.1, 
                251.1, 
                137.4, 
                74, 
                154.7
            ], 
            [
                45.6, 
                62.3, 
                87.7, 
                0, 
                91.9, 
                43.3, 
                197.3, 
                86.4, 
                73.5, 
                67
            ], 
            [
                137.5, 
                110.8, 
                136.2, 
                91.9, 
                0, 
                135.2, 
                268.3, 
                70.2, 
                62.2, 
                127.3
            ], 
            [
                31.9, 
                105.6, 
                97.1, 
                43.3, 
                135.2, 
                0, 
                154, 
                129.7, 
                116.8, 
                80.1
            ], 
            [
                185.9, 
                259.6, 
                251.1, 
                197.3, 
                268.3, 
                154, 
                0, 
                198.1, 
                270.8, 
                141
            ], 
            [
                132, 
                112, 
                137.4, 
                86.4, 
                70.2, 
                129.7, 
                198.1, 
                0, 
                96.2, 
                57.1
            ], 
            [
                119.1, 
                48.6, 
                74, 
                73.5, 
                62.2, 
                116.8, 
                270.8, 
                96.2, 
                0, 
                140.5
            ], 
            [
                90.2, 
                129.3, 
                154.7, 
                67, 
                127.3, 
                80.1, 
                141, 
                57.1, 
                140.5, 
                0
            ]
        ], 
        "weight_matrix": [
            [
                0, 
                3, 
                3, 
                3, 
                3, 
                3, 
                3, 
                3, 
                3, 
                3
            ], 
            [
                3, 
                0, 
                3, 
                3, 
                3, 
                3, 
                3, 
                3, 
                3, 
                3
            ], 
            [
                3, 
                3, 
                0, 
                3, 
                3, 
                3, 
                3, 
                3, 
                3, 
                3
            ], 
            [
                3, 
                3, 
                3, 
                0, 
                3, 
                3, 
                3, 
                3, 
                3, 
                3
            ], 
            [
                3, 
                3, 
                3, 
                3, 
                0, 
                3, 
                3, 
                3, 
                3, 
                3
            ], 
            [
                3, 
                3, 
                3, 
                3, 
                3, 
                0, 
                3, 
                3, 
                3, 
                3
            ], 
            [
                3, 
                3, 
                3, 
                3, 
                3, 
                3, 
                0, 
                3, 
                3, 
                3
            ], 
            [
                3, 
                3, 
                3, 
                3, 
                3, 
                3, 
                3, 
                0, 
                3, 
                3
            ], 
            [
                3, 
                3, 
                3, 
                3, 
                3, 
                3, 
                3, 
                3, 
                0, 
                3
            ], 
            [
                3, 
                3, 
                3, 
                3, 
                3, 
                3, 
                3, 
                3, 
                3, 
                0
            ]
        ], 
        "city_names": [
            "Amsterdam", 
            "Rotterdam", 
            "Den Haag", 
            "Utrecht", 
            "Eindhoven", 
            "Almere", 
            "Groningen", 
            "Nijmegen", 
            "Breda", 
            "Apeldoorn"
        ], 
        "reward_matrix": [
            [
                0, 
                73456, 
                83796, 
                91775, 
                54364, 
                97352, 
                34661, 
                56603, 
                61855, 
                73619
            ], 
            [
                73456, 
                0, 
                99999, 
                84977, 
                65233, 
                67350, 
                4659, 
                64745, 
                90554, 
                57702
            ], 
            [
                83796, 
                99999, 
                0, 
                74637, 
                54893, 
                70810, 
                8119, 
                54405, 
                80214, 
                47362
            ], 
            [
                91775, 
                84977, 
                74637, 
                0, 
                72927, 
                92712, 
                30020, 
                75166, 
                80418, 
                83064
            ], 
            [
                54364, 
                65233, 
                54893, 
                72927, 
                0, 
                55300, 
                1117, 
                81761, 
                85018, 
                58516
            ], 
            [
                97352, 
                67350, 
                70810, 
                92712, 
                55300, 
                0, 
                47647, 
                57539, 
                62791, 
                77731
            ], 
            [
                34661, 
                4659, 
                8119, 
                30020, 
                1117, 
                47647, 
                0, 
                29695, 
                100, 
                52939
            ], 
            [
                56603, 
                64745, 
                54405, 
                75166, 
                81761, 
                57539, 
                29695, 
                0, 
                71177, 
                87094
            ], 
            [
                61855, 
                90554, 
                80214, 
                80418, 
                85018, 
                62791, 
                100, 
                71177, 
                0, 
                53143
            ], 
            [
                73619, 
                57702, 
                47362, 
                83064, 
                58516, 
                77731, 
                52939, 
                87094, 
                53143, 
                0
            ]
        ], 
        "probability_matrix": [
            [
                0, 
                0.022722028066797954, 
                0.16152078036296888, 
                0.0873380690515669, 
                0.13176444687586833, 
                0.15158976570721855, 
                0.08225662335287802, 
                0.1176615742285581, 
                0.10757344772000826, 
                0.13757326463413486
            ], 
            [
                0.16915369250036427, 
                0, 
                0.02849491642152103, 
                0.014516543139260955, 
                0.07016403484640849, 
                0.12112533600419319, 
                0.052487865176984214, 
                0.21717838652033883, 
                0.16258136647186502, 
                0.16429785891906387
            ], 
            [
                0.10718959918818247, 
                0.03339327378180832, 
                0, 
                0.198537127198915, 
                0.1628537555166702, 
                0.03566086462692578, 
                0.08689844824086457, 
                0.12017292472772471, 
                0.20013920893734966, 
                0.055154797781559545
            ], 
            [
                0.016724113521084886, 
                0.1668897129998155, 
                0.1130114252007195, 
                0, 
                0.2075193798610737, 
                0.1321531245643258, 
                0.0010828691680190307, 
                0.05671555351430716, 
                0.11874929639642665, 
                0.18715452477422773
            ], 
            [
                0.2087829741197237, 
                0.07874328538695406, 
                0.00707157045540388, 
                0.08971270970548313, 
                0, 
                0.07492174128294171, 
                0.1621668305995292, 
                0.06286229882018511, 
                0.10133353619447598, 
                0.21440505343530297
            ], 
            [
                0.062447073316926886, 
                0.05995084915626215, 
                0.1564378293505144, 
                0.2182974710868464, 
                0.06634150944154255, 
                0, 
                0.020852500320534807, 
                0.202150331425422, 
                0.11955966960038004, 
                0.09396276630157083
            ], 
            [
                0.11745646616276166, 
                0.22608796495010988, 
                0.16013845438568114, 
                0.10879302718273988, 
                0.0845927156531781, 
                0.020741374541855834, 
                0, 
                0.15518854943396027, 
                0.051183956021228286, 
                0.07581749166848491
            ], 
            [
                0.09425613288610327, 
                0.05662703403332009, 
                0.1468492717111929, 
                0.1224704303232344, 
                0.07653548756751062, 
                0.06898710757485399, 
                0.14649122589558133, 
                0, 
                0.13194538721330126, 
                0.15583792279490216
            ], 
            [
                0.019692404037787922, 
                0.0920864347418512, 
                0.14325497275731675, 
                0.13750309195274496, 
                0.03742773137075086, 
                0.2309709080422237, 
                0.01765284196637671, 
                0.11532036561220572, 
                0, 
                0.20609124951874205
            ], 
            [
                0.13984326537936223, 
                0.23344312240808318, 
                0.04688738034335866, 
                0.05340378525147273, 
                0.21730277031057668, 
                0.005145401465419238, 
                0.056240219092614584, 
                0.014080346530313417, 
                0.23365370921879927, 
                0
            ]
        ]
    }, 
    "vehicle_capacities": [
        5, 
        10, 
        10, 
        15, 
        30, 
        30, 
        30, 
        30, 
        30, 
        30
    ]
}