{
    "vehicle_cost_per_km": [
        5, 
        5, 
        5, 
        5, 
        5
    ], 
    "runs": [
        {
            "avg_task_cost_vs_number_of_task": [
                1699.5, 
                1210.25, 
                968.6666666666666, 
                726.5, 
                651.7, 
                566.75, 
                513.2857142857143, 
                449.125, 
                439.3888888888889, 
                424.4, 
                391, 
                381.25000000000006, 
                351.38461538461536, 
                339.74999999999994, 
                311.46666666666664, 
                337.28125000000006, 
                294.1470588235294, 
                303.8888888888889, 
                322.3947368421053, 
                285.175, 
                274.0952380952381, 
                270.72727272727275, 
                298.1304347826087, 
                268.2083333333333, 
                254.96, 
                250.69230769230768, 
                317.7037037037037, 
                248.58928571428575, 
                300.7586206896552, 
                262.9166666666667
            ], 
            "number_of_vehicles": 5
        }
    ], 
    "vehicle_starting_positions": [
        "Amsterdam", 
        "Rotterdam", 
        "Den Haag", 
        "Utrecht", 
        "Eindhoven", 
        "Almere", 
        "Groningen", 
        "Nijmegen", 
        "Breda", 
        "Apeldoorn"
    ], 
    "task_distribution": {
        "distance_matrix": [
            [
                0, 
                90.6, 
                65.2, 
                45.6, 
                137.5, 
                31.9, 
                185.9, 
                132, 
                119.1, 
                90.2
            ], 
            [
                90.6, 
                0, 
                25.4, 
                62.3, 
                110.8, 
                105.6, 
                259.6, 
                112, 
                48.6, 
                129.3
            ], 
            [
                65.2, 
                25.4, 
                0, 
                87.7, 
                136.2, 
                97.1, 
                251.1, 
                137.4, 
                74, 
                154.7
            ], 
            [
                45.6, 
                62.3, 
                87.7, 
                0, 
                91.9, 
                43.3, 
                197.3, 
                86.4, 
                73.5, 
                67
            ], 
            [
                137.5, 
                110.8, 
                136.2, 
                91.9, 
                0, 
                135.2, 
                268.3, 
                70.2, 
                62.2, 
                127.3
            ], 
            [
                31.9, 
                105.6, 
                97.1, 
                43.3, 
                135.2, 
                0, 
                154, 
                129.7, 
                116.8, 
                80.1
            ], 
            [
                185.9, 
                259.6, 
                251.1, 
                197.3, 
                268.3, 
                154, 
                0, 
                198.1, 
                270.8, 
                141
            ], 
            [
                132, 
                112, 
                137.4, 
                86.4, 
                70.2, 
                129.7, 
                198.1, 
                0, 
                96.2, 
                57.1
            ], 
            [
                119.1, 
                48.6, 
                74, 
                73.5, 
                62.2, 
                116.8, 
                270.8, 
                96.2, 
                0, 
                140.5
            ], 
            [
                90.2, 
                129.3, 
                154.7, 
                67, 
                127.3, 
                80.1, 
                141, 
                57.1, 
                140.5, 
                0
            ]
        ], 
        "weight_matrix": [
            [
                0, 
                3, 
                3, 
                3, 
                3, 
                3, 
                3, 
                3, 
                3, 
                3
            ], 
            [
                3, 
                0, 
                3, 
                3, 
                3, 
                3, 
                3, 
                3, 
                3, 
                3
            ], 
            [
                3, 
                3, 
                0, 
                3, 
                3, 
                3, 
                3, 
                3, 
                3, 
                3
            ], 
            [
                3, 
                3, 
                3, 
                0, 
                3, 
                3, 
                3, 
                3, 
                3, 
                3
            ], 
            [
                3, 
                3, 
                3, 
                3, 
                0, 
                3, 
                3, 
                3, 
                3, 
                3
            ], 
            [
                3, 
                3, 
                3, 
                3, 
                3, 
                0, 
                3, 
                3, 
                3, 
                3
            ], 
            [
                3, 
                3, 
                3, 
                3, 
                3, 
                3, 
                0, 
                3, 
                3, 
                3
            ], 
            [
                3, 
                3, 
                3, 
                3, 
                3, 
                3, 
                3, 
                0, 
                3, 
                3
            ], 
            [
                3, 
                3, 
                3, 
                3, 
                3, 
                3, 
                3, 
                3, 
                0, 
                3
            ], 
            [
                3, 
                3, 
                3, 
                3, 
                3, 
                3, 
                3, 
                3, 
                3, 
                0
            ]
        ], 
        "city_names": [
            "Amsterdam", 
            "Rotterdam", 
            "Den Haag", 
            "Utrecht", 
            "Eindhoven", 
            "Almere", 
            "Groningen", 
            "Nijmegen", 
            "Breda", 
            "Apeldoorn"
        ], 
        "reward_matrix": [
            [
                0, 
                73456, 
                83796, 
                91775, 
                54364, 
                97352, 
                34661, 
                56603, 
                61855, 
                73619
            ], 
            [
                73456, 
                0, 
                99999, 
                84977, 
                65233, 
                67350, 
                4659, 
                64745, 
                90554, 
                57702
            ], 
            [
                83796, 
                99999, 
                0, 
                74637, 
                54893, 
                70810, 
                8119, 
                54405, 
                80214, 
                47362
            ], 
            [
                91775, 
                84977, 
                74637, 
                0, 
                72927, 
                92712, 
                30020, 
                75166, 
                80418, 
                83064
            ], 
            [
                54364, 
                65233, 
                54893, 
                72927, 
                0, 
                55300, 
                1117, 
                81761, 
                85018, 
                58516
            ], 
            [
                97352, 
                67350, 
                70810, 
                92712, 
                55300, 
                0, 
                47647, 
                57539, 
                62791, 
                77731
            ], 
            [
                34661, 
                4659, 
                8119, 
                30020, 
                1117, 
                47647, 
                0, 
                29695, 
                100, 
                52939
            ], 
            [
                56603, 
                64745, 
                54405, 
                75166, 
                81761, 
                57539, 
                29695, 
                0, 
                71177, 
                87094
            ], 
            [
                61855, 
                90554, 
                80214, 
                80418, 
                85018, 
                62791, 
                100, 
                71177, 
                0, 
                53143
            ], 
            [
                73619, 
                57702, 
                47362, 
                83064, 
                58516, 
                77731, 
                52939, 
                87094, 
                53143, 
                0
            ]
        ], 
        "probability_matrix": [
            [
                0, 
                0.036033096213832876, 
                0.0794053407772061, 
                0.10717767927761665, 
                0.008621605393821362, 
                0.267799114220091, 
                0.11798588784340021, 
                0.2663461410239646, 
                0.02574753416314142, 
                0.0908836010869258
            ], 
            [
                0.1401716736738809, 
                0, 
                0.12503979636546864, 
                0.10946959272988725, 
                0.05416232056354829, 
                0.19246894908679613, 
                0.14458170793690817, 
                0.021044502027187526, 
                0.04264178030209322, 
                0.17041967731422986
            ], 
            [
                0.09332099863950415, 
                0.07421374563806632, 
                0, 
                0.03406616082033908, 
                0.17885921727857942, 
                0.14019682457353758, 
                0.1497159966753418, 
                0.035427407719843984, 
                0.14006204856118049, 
                0.15413760009360708
            ], 
            [
                0.010958315879992402, 
                0.09683269642505253, 
                0.1302789408773622, 
                0, 
                0.13280827752564944, 
                0.10236694995075839, 
                0.06725364740430795, 
                0.17064423429259606, 
                0.1338137934178425, 
                0.15504314422643856
            ], 
            [
                0.09469747513528728, 
                0.19677992719292975, 
                0.14475135813419548, 
                0.08955227665261488, 
                0, 
                0.05846738407731948, 
                0.12179331173177627, 
                0.06415017112662183, 
                0.18908321527529548, 
                0.04072488067395961
            ], 
            [
                0.1428704349002581, 
                0.13244472927833528, 
                0.08105559952128298, 
                0.14532872391210197, 
                0.05163091970375484, 
                0, 
                0.15616741596384068, 
                0.05950540600975625, 
                0.16675490029949, 
                0.06424187041117983
            ], 
            [
                0.16470055678998685, 
                0.0049753121692163406, 
                0.17540486550808643, 
                0.13975306737479692, 
                0.09504395342146088, 
                0.12274462706744292, 
                0, 
                0.09469975493120202, 
                0.14164798352447194, 
                0.06102987921333561
            ], 
            [
                0.23207776044049036, 
                0.21528290152396953, 
                0.031478682105389046, 
                0.1417323740473884, 
                0.0922047640177754, 
                0.1275362469148319, 
                0.07555411777544907, 
                0, 
                0.07475586916106466, 
                0.009377284013641534
            ], 
            [
                0.09115499966907, 
                0.0007806484507976527, 
                0.09077911906726464, 
                0.0004749872120314245, 
                0.014621966911708232, 
                0.260193485227775, 
                0.18043373003223404, 
                0.08533231601434856, 
                0, 
                0.2762287474147705
            ], 
            [
                0.07228426841964973, 
                0.07132563691957439, 
                0.1967324912426783, 
                0.0769056026912724, 
                0.20363752981389877, 
                0.15178803204109434, 
                0.03257161281246259, 
                0.12496637498418185, 
                0.06978845107518766, 
                0
            ]
        ]
    }, 
    "vehicle_capacities": [
        20, 
        20, 
        20, 
        20, 
        25, 
        30, 
        30, 
        30, 
        30, 
        30
    ]
}