{
    "vehicle_cost_per_km": [
        5, 
        5, 
        5, 
        5, 
        5
    ], 
    "runs": [
        {
            "avg_task_cost_vs_number_of_task": [
                459.5, 
                527.25, 
                520.8333333333334, 
                422.375, 
                453.8, 
                405.25, 
                373.85714285714283, 
                359.1875, 
                325.5, 
                301.6, 
                372.95454545454555, 
                330.25000000000006, 
                329.0384615384616, 
                307.0357142857143, 
                302.76666666666665, 
                288.5625, 
                302.2058823529412, 
                281.77777777777777, 
                259.2631578947368, 
                268.925, 
                318.26190476190476, 
                304.40909090909093, 
                264.2608695652174, 
                263.4791666666667, 
                270.2, 
                254.5192307692308, 
                220, 
                248.625, 
                254.0344827586207, 
                267.8333333333333
            ], 
            "number_of_vehicles": 5
        }
    ], 
    "vehicle_starting_positions": [
        "Amsterdam", 
        "Rotterdam", 
        "Den Haag", 
        "Utrecht", 
        "Eindhoven", 
        "Almere", 
        "Groningen", 
        "Nijmegen", 
        "Breda", 
        "Apeldoorn"
    ], 
    "task_distribution": {
        "distance_matrix": [
            [
                0, 
                90.6, 
                65.2, 
                45.6, 
                137.5, 
                31.9, 
                185.9, 
                132, 
                119.1, 
                90.2
            ], 
            [
                90.6, 
                0, 
                25.4, 
                62.3, 
                110.8, 
                105.6, 
                259.6, 
                112, 
                48.6, 
                129.3
            ], 
            [
                65.2, 
                25.4, 
                0, 
                87.7, 
                136.2, 
                97.1, 
                251.1, 
                137.4, 
                74, 
                154.7
            ], 
            [
                45.6, 
                62.3, 
                87.7, 
                0, 
                91.9, 
                43.3, 
                197.3, 
                86.4, 
                73.5, 
                67
            ], 
            [
                137.5, 
                110.8, 
                136.2, 
                91.9, 
                0, 
                135.2, 
                268.3, 
                70.2, 
                62.2, 
                127.3
            ], 
            [
                31.9, 
                105.6, 
                97.1, 
                43.3, 
                135.2, 
                0, 
                154, 
                129.7, 
                116.8, 
                80.1
            ], 
            [
                185.9, 
                259.6, 
                251.1, 
                197.3, 
                268.3, 
                154, 
                0, 
                198.1, 
                270.8, 
                141
            ], 
            [
                132, 
                112, 
                137.4, 
                86.4, 
                70.2, 
                129.7, 
                198.1, 
                0, 
                96.2, 
                57.1
            ], 
            [
                119.1, 
                48.6, 
                74, 
                73.5, 
                62.2, 
                116.8, 
                270.8, 
                96.2, 
                0, 
                140.5
            ], 
            [
                90.2, 
                129.3, 
                154.7, 
                67, 
                127.3, 
                80.1, 
                141, 
                57.1, 
                140.5, 
                0
            ]
        ], 
        "weight_matrix": [
            [
                0, 
                3, 
                3, 
                3, 
                3, 
                3, 
                3, 
                3, 
                3, 
                3
            ], 
            [
                3, 
                0, 
                3, 
                3, 
                3, 
                3, 
                3, 
                3, 
                3, 
                3
            ], 
            [
                3, 
                3, 
                0, 
                3, 
                3, 
                3, 
                3, 
                3, 
                3, 
                3
            ], 
            [
                3, 
                3, 
                3, 
                0, 
                3, 
                3, 
                3, 
                3, 
                3, 
                3
            ], 
            [
                3, 
                3, 
                3, 
                3, 
                0, 
                3, 
                3, 
                3, 
                3, 
                3
            ], 
            [
                3, 
                3, 
                3, 
                3, 
                3, 
                0, 
                3, 
                3, 
                3, 
                3
            ], 
            [
                3, 
                3, 
                3, 
                3, 
                3, 
                3, 
                0, 
                3, 
                3, 
                3
            ], 
            [
                3, 
                3, 
                3, 
                3, 
                3, 
                3, 
                3, 
                0, 
                3, 
                3
            ], 
            [
                3, 
                3, 
                3, 
                3, 
                3, 
                3, 
                3, 
                3, 
                0, 
                3
            ], 
            [
                3, 
                3, 
                3, 
                3, 
                3, 
                3, 
                3, 
                3, 
                3, 
                0
            ]
        ], 
        "city_names": [
            "Amsterdam", 
            "Rotterdam", 
            "Den Haag", 
            "Utrecht", 
            "Eindhoven", 
            "Almere", 
            "Groningen", 
            "Nijmegen", 
            "Breda", 
            "Apeldoorn"
        ], 
        "reward_matrix": [
            [
                0, 
                73456, 
                83796, 
                91775, 
                54364, 
                97352, 
                34661, 
                56603, 
                61855, 
                73619
            ], 
            [
                73456, 
                0, 
                99999, 
                84977, 
                65233, 
                67350, 
                4659, 
                64745, 
                90554, 
                57702
            ], 
            [
                83796, 
                99999, 
                0, 
                74637, 
                54893, 
                70810, 
                8119, 
                54405, 
                80214, 
                47362
            ], 
            [
                91775, 
                84977, 
                74637, 
                0, 
                72927, 
                92712, 
                30020, 
                75166, 
                80418, 
                83064
            ], 
            [
                54364, 
                65233, 
                54893, 
                72927, 
                0, 
                55300, 
                1117, 
                81761, 
                85018, 
                58516
            ], 
            [
                97352, 
                67350, 
                70810, 
                92712, 
                55300, 
                0, 
                47647, 
                57539, 
                62791, 
                77731
            ], 
            [
                34661, 
                4659, 
                8119, 
                30020, 
                1117, 
                47647, 
                0, 
                29695, 
                100, 
                52939
            ], 
            [
                56603, 
                64745, 
                54405, 
                75166, 
                81761, 
                57539, 
                29695, 
                0, 
                71177, 
                87094
            ], 
            [
                61855, 
                90554, 
                80214, 
                80418, 
                85018, 
                62791, 
                100, 
                71177, 
                0, 
                53143
            ], 
            [
                73619, 
                57702, 
                47362, 
                83064, 
                58516, 
                77731, 
                52939, 
                87094, 
                53143, 
                0
            ]
        ], 
        "probability_matrix": [
            [
                0, 
                0.009654815670060114, 
                0.1983937514172975, 
                0.09377276273276755, 
                0.15018793382961412, 
                0.0894677549108051, 
                0.1280698247121348, 
                0.1938912898175836, 
                0.05712608625364796, 
                0.07943578065608937
            ], 
            [
                0.022215076331712963, 
                0, 
                0.1600783821400699, 
                0.1872251999299821, 
                0.10565041326848837, 
                0.13897541033116237, 
                0.11547649356213473, 
                0.10894265101701324, 
                0.16065463773456423, 
                0.0007817356848721847
            ], 
            [
                0.06745645000813694, 
                0.1519640204332554, 
                0, 
                0.13552824355960305, 
                0.1832559287365437, 
                0.013700807726525863, 
                0.1335605251596226, 
                0.1869024728742565, 
                0.06485788656383996, 
                0.06277366493821576
            ], 
            [
                0.07902508147599327, 
                0.1544103875489157, 
                0.09776571014177163, 
                0, 
                0.11904247376373381, 
                0.09062895195820134, 
                0.14532311057423536, 
                0.09308794880973754, 
                0.0777879528366292, 
                0.14292838289078222
            ], 
            [
                0.15937581112064017, 
                0.03916039838300229, 
                0.043167066077119266, 
                0.145309598013242, 
                0, 
                0.1188267749539619, 
                0.05215948449275905, 
                0.20574779749062838, 
                0.13966003069319036, 
                0.09659303877545661
            ], 
            [
                0.1285370749093206, 
                0.03161678532023838, 
                0.00878871738112685, 
                0.20599377639508043, 
                0.04339402327137044, 
                0, 
                0.20535279217778027, 
                0.11725547839160759, 
                0.11612789391970979, 
                0.14293345823376574
            ], 
            [
                0.009512135705460643, 
                0.16872670812127455, 
                0.08423952768711691, 
                0.04732331272873904, 
                0.09788907090862392, 
                0.1389245612250074, 
                0, 
                0.2751008334665316, 
                0.10517746158937868, 
                0.07310638856786728
            ], 
            [
                0.21366395664443907, 
                0.11993322118761766, 
                0.21024173355313489, 
                0.0679530688628319, 
                0.1500554123098533, 
                0.048498963763357855, 
                0.0014994103442597668, 
                0, 
                0.03145740294380992, 
                0.15669683039069554
            ], 
            [
                0.23294477462966787, 
                0.023367489029058608, 
                0.21454265402286968, 
                0.004201190056331907, 
                0.03464980118813404, 
                0.13265142384865217, 
                0.23640017982229083, 
                0.06727145345958, 
                0, 
                0.05397103394341485
            ], 
            [
                0.04963932410295538, 
                0.18739296321351712, 
                0.10485641061265331, 
                0.11940819261472004, 
                0.14295023562293932, 
                0.006342330805978097, 
                0.11969968081533525, 
                0.10362361622480695, 
                0.16608724598709457, 
                0
            ]
        ]
    }, 
    "vehicle_capacities": [
        10, 
        20, 
        20, 
        20, 
        30, 
        30, 
        30, 
        30, 
        30, 
        30
    ]
}